sdk/__init__.py
sdk/endpoints.py
sdk/sdk.py
lotr_onexyz-0.0.1.dist-info/METADATA
lotr_onexyz-0.0.1.dist-info/WHEEL
lotr_onexyz-0.0.1.dist-info/top_level.txt
lotr_onexyz-0.0.1.dist-info/RECORD
