Metadata-Version: 2.1
Name: lotr-onexyz
Version: 0.0.1
Summary: LOTR coding test
Author: Alex
Author-email: 
Requires-Python: >=3.10.9
Requires-Dist: requests
